<?xml version="1.0" encoding="UTF-8"?>

<FLOW VERSION="1.0" CLEANUP="false">
  <COMMENT></COMMENT>

  <!-- nodes -->

<INVOKE NAME="openweatherclient_bb" SERVICE="OpenWeatherClient.REST.openweatherclient_.services:CurrentWeatherData">
  <COMMENT></COMMENT>

  <!-- nodes -->

<MAP MODE="INPUT">
  <COMMENT></COMMENT>
  <MAPTARGET>

<Values version="2.0">
  <record name="xml" javaclass="com.wm.util.Values">
    <value name="node_type">record</value>
    <value name="node_subtype">unknown</value>
    <value name="is_public">false</value>
    <value name="displayName"></value>
    <value name="favorite"></value>
    <value name="tags"></value>
    <value name="since"></value>
    <value name="deprecated"></value>
    <value name="is_visible"></value>
    <value name="field_type">record</value>
    <value name="field_is_jsonSchema">true</value>
    <value name="field_dim">0</value>
    <value name="wrapper_type">IData</value>
    <array name="field_content_type" type="record" depth="1">
      <record javaclass="com.wm.util.Values">
        <record name="extendedProperties" javaclass="com.wm.util.Values">
          <record name="extensionName" javaclass="com.wm.util.Values">
            <value name="key">extensionName</value>
            <value name="value">openapi</value>
            <value name="type">STRING</value>
          </record>
          <record name="extensionVersion" javaclass="com.wm.util.Values">
            <value name="key">extensionVersion</value>
            <value name="value">3.0.2</value>
            <value name="type">STRING</value>
          </record>
        </record>
      </record>
    </array>
    <value name="nillable">true</value>
    <Boolean name="readOnly">false</Boolean>
    <Boolean name="writeOnly">false</Boolean>
    <array name="rec_fields" type="record" depth="1">
      <record javaclass="com.wm.util.Values">
        <value name="node_type">record</value>
        <value name="node_subtype">unknown</value>
        <value name="node_comment"></value>
        <record name="node_hints" javaclass="com.wm.util.Values">
          <value name="field_largerEditor">false</value>
          <value name="field_password">false</value>
        </record>
        <value name="is_public">false</value>
        <value name="field_name">params</value>
        <value name="field_type">record</value>
        <value name="field_dim">0</value>
        <value name="field_opt">true</value>
        <value name="wrapper_type">IData</value>
        <value name="nillable">true</value>
        <value name="form_qualified">false</value>
        <value name="is_global">false</value>
        <array name="rec_fields" type="record" depth="1">
          <record javaclass="com.wm.util.Values">
            <value name="node_type">record</value>
            <value name="node_subtype">unknown</value>
            <value name="node_comment"></value>
            <record name="node_hints" javaclass="com.wm.util.Values">
              <value name="field_largerEditor">false</value>
              <value name="field_password">false</value>
            </record>
            <value name="is_public">false</value>
            <value name="field_name">query</value>
            <value name="field_type">record</value>
            <value name="field_dim">0</value>
            <value name="field_opt">true</value>
            <value name="wrapper_type">IData</value>
            <value name="nillable">true</value>
            <value name="form_qualified">false</value>
            <value name="is_global">false</value>
            <array name="rec_fields" type="record" depth="1">
              <record javaclass="com.wm.util.Values">
                <value name="node_type">field</value>
                <value name="node_subtype">unknown</value>
                <value name="node_comment"></value>
                <record name="node_hints" javaclass="com.wm.util.Values">
                  <value name="field_usereditable">true</value>
                  <value name="field_largerEditor">false</value>
                  <value name="field_password">false</value>
                </record>
                <value name="is_public">false</value>
                <value name="field_name">q</value>
                <value name="field_type">string</value>
                <value name="field_is_jsonSchema">true</value>
                <value name="field_dim">0</value>
                <value name="field_opt">true</value>
                <array name="field_options" type="value" depth="1">
                </array>
                <array name="field_content_type" type="record" depth="1">
                  <record javaclass="com.wm.util.Values">
                    <record name="type" javaclass="com.wm.util.Values">
                      <value name="key">type</value>
                      <value name="value">string</value>
                      <value name="type">STRING</value>
                    </record>
                    <record name="extendedProperties" javaclass="com.wm.util.Values">
                      <record name="extensionName" javaclass="com.wm.util.Values">
                        <value name="key">extensionName</value>
                        <value name="value">openapi</value>
                        <value name="type">STRING</value>
                      </record>
                      <record name="extensionVersion" javaclass="com.wm.util.Values">
                        <value name="key">extensionVersion</value>
                        <value name="value">3.0.2</value>
                        <value name="type">STRING</value>
                      </record>
                    </record>
                  </record>
                </array>
                <value name="nillable">false</value>
                <Boolean name="readOnly">false</Boolean>
                <Boolean name="writeOnly">false</Boolean>
              </record>
              <record javaclass="com.wm.util.Values">
                <value name="node_type">field</value>
                <value name="node_subtype">unknown</value>
                <value name="node_comment"></value>
                <record name="node_hints" javaclass="com.wm.util.Values">
                  <value name="field_usereditable">true</value>
                  <value name="field_largerEditor">false</value>
                  <value name="field_password">false</value>
                </record>
                <value name="is_public">false</value>
                <value name="field_name">appid</value>
                <value name="field_type">string</value>
                <value name="field_is_jsonSchema">true</value>
                <value name="field_dim">0</value>
                <value name="field_opt">true</value>
                <array name="field_options" type="value" depth="1">
                </array>
                <array name="field_content_type" type="record" depth="1">
                  <record javaclass="com.wm.util.Values">
                    <record name="type" javaclass="com.wm.util.Values">
                      <value name="key">type</value>
                      <value name="value">string</value>
                      <value name="type">STRING</value>
                    </record>
                    <record name="extendedProperties" javaclass="com.wm.util.Values">
                      <record name="extensionName" javaclass="com.wm.util.Values">
                        <value name="key">extensionName</value>
                        <value name="value">openapi</value>
                        <value name="type">STRING</value>
                      </record>
                      <record name="extensionVersion" javaclass="com.wm.util.Values">
                        <value name="key">extensionVersion</value>
                        <value name="value">3.0.2</value>
                        <value name="type">STRING</value>
                      </record>
                    </record>
                  </record>
                </array>
                <value name="nillable">false</value>
                <Boolean name="readOnly">false</Boolean>
                <Boolean name="writeOnly">false</Boolean>
              </record>
            </array>
            <value name="modifiable">true</value>
          </record>
        </array>
        <value name="modifiable">true</value>
      </record>
    </array>
    <value name="modifiable">true</value>
  </record>
</Values>
</MAPTARGET>
  <MAPSOURCE>

<Values version="2.0">
  <record name="xml" javaclass="com.wm.util.Values">
    <value name="node_type">record</value>
    <value name="node_subtype">unknown</value>
    <value name="is_public">false</value>
    <value name="field_type">record</value>
    <value name="field_dim">0</value>
    <value name="nillable">true</value>
    <value name="form_qualified">false</value>
    <value name="is_global">false</value>
    <array name="rec_fields" type="record" depth="1">
    </array>
    <value name="modifiable">true</value>
  </record>
</Values>
</MAPSOURCE>

  <!-- nodes -->

<MAPSET NAME="Setter" OVERWRITE="true" VARIABLES="false" GLOBALVARIABLES="false" FIELD="/params;2;0/query;2;0/q;1;0">
  <DATA ENCODING="XMLValues" I18N="true">

<Values version="2.0">
  <value name="xml">London</value>
</Values>
</DATA>
</MAPSET>

<MAPSET NAME="Setter" OVERWRITE="true" VARIABLES="false" GLOBALVARIABLES="false" FIELD="/params;2;0/query;2;0/appid;1;0">
  <DATA ENCODING="XMLValues" I18N="true">

<Values version="2.0">
  <value name="xml">735e300365db5439fb2ffd8a5e7b693a</value>
</Values>
</DATA>
</MAPSET>
</MAP>

<MAP MODE="OUTPUT">
  <COMMENT></COMMENT>
</MAP>
</INVOKE>

<INVOKE NAME="siqafullyloadedpackagetests" SERVICE="SIQAPartialLoadTests.data:Empty">
  <COMMENT></COMMENT>
</INVOKE>
</FLOW>
